{
	"localizedName": "Ash",
	"description": "It turns your enemies... into ash.",
	"health": 12548,
	"size": 6,
	"reload": 160,
	"range": 180,
	"shootCone": 20,
	"heatColor": "FF0000",
	"ammoUseEffect": "none",
	"rotatespeed": 3.5,
	"recoil": 3,
	"powerUse": 22.06,
	"hasPower": true,
	"targetAir": false,
	"cooldown": 0.022,
	"requirements": [
		{ "item": "silicon", "amount": 100 },
		{ "item": "titanium", "amount": 100 },
		{ "item": "undulium", "amount": 100 },
		{ "item": "dherium", "amount": 100 },
		{ "item": "surge-alloy", "amount": 50 },
		{ "item": "wizz", "amount": 50 }
	],
	"category": "turret",
	"research": "meltdown"
}